setup.py
sprt/__init__.py
sprt/maxsprt.py
sprt/sprt.py
sprt.egg-info/PKG-INFO
sprt.egg-info/SOURCES.txt
sprt.egg-info/dependency_links.txt
sprt.egg-info/not-zip-safe
sprt.egg-info/top_level.txt