Metadata-Version: 1.1
Name: sprt
Version: 0.0.1
Summary: Python package to do sequential probability ratio test
Home-page: https://github.com/ContaTP/Sequential-Probability-Ratio-Test
Author: Zhenning Yu
Author-email: yuzhenning.bio@gmail.com
License: GPLv3
Keywords: sequential analysis,sprt,likelihood,likelihood ratio,Wald
Platform: UNKNOWN
Classifier: Development Status :: 5 - Production/Stable
Classifier: Intended Audience :: Science/Research
Classifier: Intended Audience :: Healthcare Industry
Classifier: Topic :: Scientific/Engineering
Classifier: Topic :: Scientific/Engineering :: Medical Science Apps.
Classifier: License :: OSI Approved :: GNU General Public License v3 (GPLv3)
Classifier: Programming Language :: Python :: 2.7
Classifier: Programming Language :: Python :: 3
Classifier: Programming Language :: Python :: 3.3
Classifier: Programming Language :: Python :: 3.4
Classifier: Programming Language :: Python :: 3.5
Classifier: Natural Language :: English
Classifier: Operating System :: MacOS
Classifier: Operating System :: Microsoft :: Windows
Classifier: Operating System :: POSIX :: Linux
